{"pageId":"af8d51f2a19944a3","url":"https://www.medicaid.gov/federal-policy-guidance?f%5B0%5D=fpg_topics_facet%3A771&f%5B1%5D=fpg_topics_facet%3A1471&f%5B2%5D=fpg_type_facet%3A1481&f%5B3%5D=fpg_type_facet%3A1486&page=3","week":"2026-W25","runId":"2026-06-16T11-31-35-815Z-0a47d3","scannedAt":"2026-06-16T11:32:05.731Z","status":200,"depth":6,"axe":{"engine":"axe-core","version":"4.12.1","violationCount":0,"violations":{},"incompleteCount":7},"plainLanguage":{"engine":"plain-language","scored":false,"wordCount":829,"misspelledCount":6,"misspelled":["yyyy","Prepopulating"],"sentenceCount":5,"fleschReadingEase":null,"fleschKincaidGrade":null,"avgSentenceLength":null,"longSentences":0,"passiveVoiceRatio":null,"unexplainedAcronyms":["SMD","SHO","COVID","HIV","CHIPRA","ON","MARCH"],"unexplainedAcronymCount":7},"resources":{"engine":"resources","count":11,"byType":{"pdf":11},"resources":[{"url":"https://www.medicaid.gov/federal-policy-guidance/downloads/cib052423.pdf","type":"pdf"},{"url":"https://www.medicaid.gov/federal-policy-guidance/downloads/cib03042025.pdf","type":"pdf"},{"url":"https://www.medicaid.gov/federal-policy-guidance/downloads/smd25001.pdf","type":"pdf"},{"url":"https://www.medicaid.gov/federal-policy-guidance/downloads/cib01162025.pdf","type":"pdf"},{"url":"https://www.medicaid.gov/federal-policy-guidance/downloads/sho25001.pdf","type":"pdf"},{"url":"https://www.medicaid.gov/federal-policy-guidance/downloads/cib01152025.pdf","type":"pdf"},{"url":"https://www.medicaid.gov/federal-policy-guidance/downloads/sho24007.pdf","type":"pdf"},{"url":"https://www.medicaid.gov/federal-policy-guidance/downloads/cib12202024.pdf","type":"pdf"},{"url":"https://www.medicaid.gov/federal-policy-guidance/downloads/cib-12202024.pdf","type":"pdf"},{"url":"https://www.medicaid.gov/federal-policy-guidance/downloads/sho24006.pdf","type":"pdf"},{"url":"https://www.medicaid.gov/federal-policy-guidance/downloads/cib12102024.pdf","type":"pdf"}]}}