{"pageId":"1f1c635d471c6745","url":"https://www.medicare.gov/basics/get-started-with-medicare/get-more-coverage/joining-a-plan","week":"2026-W24","runId":"2026-06-13T12-59-50-685Z-dc686a","scannedAt":"2026-06-13T13:19:38.618Z","status":200,"depth":1,"axe":{"engine":"axe-core","version":"4.12.1","violationCount":0,"violations":{},"incompleteCount":49},"alfa":{"engine":"alfa","version":"0.117.0","failedCount":66,"failed":{"sia-r73":{"count":22,"ruleUrl":"https://alfa.siteimprove.com/rules/sia-r73","examples":[{"target":"<p>"},{"target":"<p>"},{"target":"<p>"}]},"sia-r17":{"count":1,"ruleUrl":"https://alfa.siteimprove.com/rules/sia-r17","examples":[{"target":"<div class=\"search-block__content\" aria-hidden=\"true\" id=\"search_form_block-content\">"}]},"sia-r111":{"count":43,"ruleUrl":"https://alfa.siteimprove.com/rules/sia-r111","examples":[{"target":"<a href=\"/\" data-listener-attached=\"true\">"},{"target":"<a href=\"/basics\" data-listener-attached=\"true\">"},{"target":"<a href=\"/basics/get-started-with-medicare\" data-listener-attached=\"true\">"}]}},"cantTellCount":36,"passedRules":40},"sustainability":{"engine":"sustainability","requests":156,"bytes":7789252,"byType":{"document":37093,"stylesheet":95241,"image":20116,"script":7412790,"font":105224,"xhr":116724,"ping":43,"fetch":2021},"co2g":1.1544,"model":"swd-v4 (co2.js)"}}