{
 "runId": "2026-06-17T11-23-38-747Z-9bf5b0",
 "week": "2026-W25",
 "domain": "www.cms.gov",
 "startedAt": "2026-06-17T11:23:39.422Z",
 "scanned": [
  "3d56ad1cc3aad73b",
  "83ff9474e21fcedf",
  "b79367dae4897578",
  "750246a741775e7e",
  "4402aaab50b92356",
  "6fccd6661c6c83e7",
  "979e6f494cd3b0ae",
  "0c5c43dcde9a50c4",
  "ad89276ce91c7251",
  "a94d2152ee715fa5",
  "908a87cb212b554d",
  "dbbc38a0dcc69c67",
  "ddaa7e0e59a6f98e",
  "f75017e87ca0e1ab",
  "be0ce484750525b4",
  "3572f6e7e3eea338",
  "c6f6efbdbf855bcf",
  "c97d0d1f95400751",
  "9228ffb79d020391",
  "6246bdf7963d08a3",
  "68593041ff8a4203",
  "741037abb645d33e",
  "251385d480d2afaa",
  "052404330423acfd",
  "50e0fe28d09d6087",
  "2b3a3b9418ab8b52",
  "97c349a24d00e984",
  "3cb6a865786419b3",
  "fb171b1daa645081",
  "64e0a58d247b6481",
  "7c5a12c6da49f443",
  "605f97f3670ca1f6",
  "3d9acee2c45ec984",
  "7efb15191a60d54b",
  "3bf9806bcb774197",
  "ef0cb1a2079d439f",
  "35bb4d8422e11982",
  "4af389410703f484",
  "ac928fc033673f63",
  "0141174018819f01",
  "9e71265fbd7b324c",
  "3dab47346863b75a",
  "8a6c3c7d9242428b",
  "417bf660168f29e8",
  "a5a8ac939439f970",
  "b55f2d36284419ce",
  "93eebaef792f84d4",
  "a049af2dfe826fbc",
  "c8fc1f236d9fab37",
  "4ac6d5440736d6ec",
  "c76e739cfbe05adf",
  "c208b519cb783eb9",
  "5bfa6a4001305f55",
  "06258a50f8636870",
  "14a6fe9db34cb317",
  "86b95f4adb73968b",
  "9eaa06121ac7100c",
  "277a093cee09c17d",
  "fc661b4d04c8fd07",
  "c8228a60dd4ca18c",
  "75fdfe77153d0f76",
  "5a2167d831aec463",
  "8aabc479e99bfc32",
  "00c18d9cab7d2951",
  "b16e793bf744baf7",
  "1031964dfb208ecd",
  "4b1ece22c9f23d9f",
  "1560e8b0bb61c9a6",
  "fc2d34ff33f65751",
  "eeb0891ca03251cf",
  "e691da369687cbd3",
  "94394e25896f19df",
  "b4bce32ed69c3144",
  "a10216ab0295a138",
  "1b62a24019e06066",
  "3c7afc31e3ea5697",
  "fa473ff182e9c1d3",
  "632444614a64b7a0",
  "3b0d5226284ed3b5",
  "f485046e57f7bc0f",
  "1a9df01426d0ab30",
  "1ed257e69b160846",
  "0ce5091a4276653d",
  "e716932464f1facf",
  "1cbf5d7b13655c63",
  "5048d34cbc6e67f1",
  "ec956cb23c3c3621",
  "838c676163e563e0",
  "bde906fd06f89a29",
  "2cd30ec7ac1bd7aa",
  "fd5de0597786b38b",
  "977a419942997a88",
  "5df4d79c82b27a10",
  "f6afa2a7f8d3babd",
  "7f1cdf2873b8c535",
  "1633bb1a06bc75ad",
  "c4cd65016ce8f016",
  "b53dbab196ce4623"
 ],
 "errors": [],
 "sampling": {
  "axe": 100,
  "alfa": 30,
  "plain-language": 50,
  "link-check": 100,
  "lighthouse": 25,
  "deprecated-html": 25,
  "resources": 100,
  "images": 50,
  "standards": 50,
  "security": 10,
  "sustainability": 25,
  "tech": 10
 },
 "linkCheck": {
  "total": 4309,
  "checked": 500,
  "brokenCount": 2,
  "broken": [
   {
    "url": "https://www.cms.gov/medicare-coverage-database/search.aspx",
    "status": 503,
    "reason": "HTTP 503",
    "foundOn": [
     "https://www.cms.gov/medicare/regulations-guidance/transmittals/2025-transmittals/r13246cp",
     "http://cms.gov/medicare/coverage/telehealth/list-services",
     "http://cms.gov/medicare/medicaid-coordination/center-program-integrity/resources/knowledge-center",
     "http://cms.gov/apps/contacts/incardir.asp",
     "http://cms.gov/medicare/coding-billing/electronic-billing/eligibility-inquiry",
     "https://www.cms.gov/medicare/regulations-guidance/transmittals/2014-transmittals?items_per_page=25&order=field_dyna_subject_formatted&page=1&sort=asc",
     "http://www.cms.gov/medicare-coverage-database/view/ncd.aspx?ncdid=222&ncdver=1",
     "https://www.cms.gov/medicare/regulations-guidance/transmittals/2014-transmittals?items_per_page=25&order=field_dyna_pe_number&page=1&sort=asc",
     "https://www.cms.gov/medicare/regulations-guidance/transmittals/2025-transmittals?items_per_page=25&order=field_dyna_subject_formatted&page=8&sort=asc",
     "https://www.cms.gov/medicare/regulations-guidance/transmittals/2025-transmittals?items_per_page=25&order=field_dyna_subject_formatted&page=10&sort=asc",
     "http://cms.gov/medicare/coding-billing/electronic-billing/professional-paper-claim-form",
     "https://www.cms.gov/regulations-and-guidance/guidance/transmittals/transmittals/r11503otn",
     "https://www.cms.gov/medicare/regulations-guidance/transmittals/2022-transmittals?items_per_page=25&order=field_dyna_pe_number&page=8&sort=asc",
     "https://www.cms.gov/medicare-coverage-database/view/ncacal-decision-memo.aspx?NCAId=134&proposed=Y",
     "https://www.cms.gov/medicare/regulations-guidance/transmittals/2025-transmittals?items_per_page=25&order=field_dyna_release_date&page=13&sort=asc",
     "https://www.cms.gov/medicare/regulations-guidance/transmittals/2025-transmittals/r13261otn",
     "https://www.cms.gov/acronyms?items_per_page=10&order=body&page=10&searchterm=&sort=asc&viewmode=grid",
     "https://www.cms.gov/medicare-coverage-database/view/article.aspx?articleid=56727&articleStatus=all&bc=3&sortBy=title&ver=18",
     "https://www.cms.gov/medicare-coverage-database/view/ncacal-tracking-sheet.aspx?NCAId=134",
     "http://cms.gov/medicare/coding-billing/electronic-billing/institutional-paper-claim-form",
     "http://www.cms.gov/medicare-coverage-database/view/ncacal-tracking-sheet.aspx?bc=17&ncacaldoctype=all&ncaid=218&sortBy=status&status=all",
     "http://cms.gov/medicare/coding-billing/electronic-billing/electronic-data-interchange-support",
     "https://www.cms.gov/regulations-and-guidance/guidance/transmittals/transmittals/r11485otn",
     "https://www.cms.gov/medicare-coverage-database/reports/local-coverage-articles-state-report.aspx?articleStatus=all&contractorNumber=all&stateRegion=all",
     "https://www.cms.gov/medicare/health-plans/medicareadvtgspecratestats/ratebooks-and-supporting-data-items/2019rates",
     "https://www.cms.gov/medicare-coverage-database/view/article.aspx?articleid=58072&articleStatus=all&bc=3&sortBy=title&ver=4",
     "https://cms.gov/",
     "https://www.cms.gov/contacts/agency-health-care-administration/general-beneficiary-contact/1553201",
     "https://www.cms.gov/medicare-coverage-database/view/ncacal-decision-memo.aspx?ncaid=239&proposed=N",
     "http://cms.gov/medicare/payment/medicare-advantage-rates-statistics/data/2019",
     "https://www.cms.gov/medicare/regulations-guidance/transmittals/2022-transmittals?items_per_page=25&order=field_dyna_issue_date&page=11&sort=desc",
     "https://www.cms.gov/medicare-coverage-database/view/article.aspx?articleid=53056&articleStatus=all&bc=3&sortBy=title&ver=15",
     "https://www.cms.gov/medicare-coverage-database/view/article.aspx?articleid=57947&articleStatus=all&bc=3&sortBy=title&ver=4",
     "https://www.cms.gov/medicare-coverage-database/view/article.aspx?articleid=55756&articleStatus=all&bc=3&sortBy=title&ver=16",
     "https://www.cms.gov/medicare/medicare-contracting/medicare-administrative-contractors/who-are-the-macs-a-b-mac-jurisdiction-f-jf",
     "https://www.cms.gov/about-cms/web-policies-important-links/no-fear-act",
     "https://www.cms.gov/medicare-coverage-database/view/article.aspx?articleId=55661&ver=3",
     "http://www.cms.gov/medicare-coverage-database/view/lcd.aspx?bc=7&contractorName=all&contractorNumber=all&lcdid=37800&lcdStatus=all&sortBy=title&ver=19",
     "http://cms.gov/medicare/enrollment-renewal/providers-suppliers/chain-ownership-system-pecos/preclusion-list",
     "https://www.cms.gov/apps/ama/license.asp?file=%2Ffiles%2Fzip%2Fjanuary-2025-opps-addendum.zip",
     "https://www.cms.gov/acronyms?page=14",
     "https://www.cms.gov/regulations-and-guidance/guidance/transmittals/2016-transmittals-items/r17p232",
     "https://www.cms.gov/medicare/regulations-guidance/transmittals/2025-transmittals/r13082cp",
     "http://cms.gov/contacts/soonercare/general-beneficiary-contact/1551696",
     "https://www.cms.gov/medicare/regulations-guidance/transmittals/2019-transmittals?items_per_page=25&order=field_dyna_transmittal_number&page=16&sort=desc",
     "https://www.cms.gov/data-research/statistics-trends-and-reports/medicare-claims-synthetic-public-use-files/cms-2008-2010-data-entrepreneurs-synthetic-public-use-file-de-synpuf/de10-sample-15",
     "https://www.cms.gov/medicare-coverage-database/view/article.aspx?articleid=57668&articleStatus=all&bc=3&sortBy=title&ver=40",
     "https://www.cms.gov/regulations-and-guidance/guidance/transmittals/2013-transmittals-items/r483pi",
     "http://cms.gov/medicare/quality/long-term-care-hospital/ltch-quality-reporting-help",
     "https://www.cms.gov/FFSProvPartProg/EmailArchive/list.asp"
    ]
   },
   {
    "url": "https://www.agentbrokerfaq.cms.gov/s/",
    "status": 0,
    "reason": "UNABLE_TO_VERIFY_LEAF_SIGNATURE",
    "foundOn": [
     "https://www.cms.gov/medicare/regulations-guidance/transmittals/2025-transmittals/r13246cp",
     "http://cms.gov/medicare/coverage/telehealth/list-services",
     "http://cms.gov/medicare/medicaid-coordination/center-program-integrity/resources/knowledge-center",
     "http://cms.gov/apps/contacts/incardir.asp",
     "http://cms.gov/medicare/coding-billing/electronic-billing/eligibility-inquiry",
     "https://www.cms.gov/medicare/regulations-guidance/transmittals/2014-transmittals?items_per_page=25&order=field_dyna_subject_formatted&page=1&sort=asc",
     "https://www.cms.gov/medicare/regulations-guidance/transmittals/2014-transmittals?items_per_page=25&order=field_dyna_pe_number&page=1&sort=asc",
     "https://www.cms.gov/medicare/regulations-guidance/transmittals/2025-transmittals?items_per_page=25&order=field_dyna_subject_formatted&page=8&sort=asc",
     "https://www.cms.gov/medicare/regulations-guidance/transmittals/2025-transmittals?items_per_page=25&order=field_dyna_subject_formatted&page=10&sort=asc",
     "http://cms.gov/medicare/coding-billing/electronic-billing/professional-paper-claim-form",
     "https://www.cms.gov/regulations-and-guidance/guidance/transmittals/transmittals/r11503otn",
     "https://www.cms.gov/medicare/regulations-guidance/transmittals/2022-transmittals?items_per_page=25&order=field_dyna_pe_number&page=8&sort=asc",
     "https://www.cms.gov/medicare/regulations-guidance/transmittals/2025-transmittals?items_per_page=25&order=field_dyna_release_date&page=13&sort=asc",
     "https://www.cms.gov/medicare/regulations-guidance/transmittals/2025-transmittals/r13261otn",
     "https://www.cms.gov/acronyms?items_per_page=10&order=body&page=10&searchterm=&sort=asc&viewmode=grid",
     "http://cms.gov/medicare/coding-billing/electronic-billing/institutional-paper-claim-form",
     "http://cms.gov/medicare/coding-billing/electronic-billing/electronic-data-interchange-support",
     "https://www.cms.gov/regulations-and-guidance/guidance/transmittals/transmittals/r11485otn",
     "https://www.cms.gov/medicare/health-plans/medicareadvtgspecratestats/ratebooks-and-supporting-data-items/2019rates",
     "https://cms.gov/",
     "https://www.cms.gov/contacts/agency-health-care-administration/general-beneficiary-contact/1553201",
     "http://cms.gov/medicare/payment/medicare-advantage-rates-statistics/data/2019",
     "https://www.cms.gov/medicare/regulations-guidance/transmittals/2022-transmittals?items_per_page=25&order=field_dyna_issue_date&page=11&sort=desc",
     "https://www.cms.gov/medicare/medicare-contracting/medicare-administrative-contractors/who-are-the-macs-a-b-mac-jurisdiction-f-jf",
     "https://www.cms.gov/about-cms/web-policies-important-links/no-fear-act",
     "http://cms.gov/medicare/enrollment-renewal/providers-suppliers/chain-ownership-system-pecos/preclusion-list",
     "https://www.cms.gov/apps/ama/license.asp?file=%2Ffiles%2Fzip%2Fjanuary-2025-opps-addendum.zip",
     "https://www.cms.gov/acronyms?page=14",
     "https://www.cms.gov/regulations-and-guidance/guidance/transmittals/2016-transmittals-items/r17p232",
     "https://www.cms.gov/medicare/regulations-guidance/transmittals/2025-transmittals/r13082cp",
     "http://cms.gov/contacts/soonercare/general-beneficiary-contact/1551696",
     "https://www.cms.gov/medicare/regulations-guidance/transmittals/2019-transmittals?items_per_page=25&order=field_dyna_transmittal_number&page=16&sort=desc",
     "https://www.cms.gov/data-research/statistics-trends-and-reports/medicare-claims-synthetic-public-use-files/cms-2008-2010-data-entrepreneurs-synthetic-public-use-file-de-synpuf/de10-sample-15",
     "https://www.cms.gov/regulations-and-guidance/guidance/transmittals/2013-transmittals-items/r483pi",
     "http://cms.gov/medicare/quality/long-term-care-hospital/ltch-quality-reporting-help",
     "https://www.cms.gov/FFSProvPartProg/EmailArchive/list.asp",
     "http://cms.gov/nosurprises/notices",
     "https://www.cms.gov/medicare/payment/prospective-payment-systems/skilled-nursing-facility-snf/list-federal-regulations/cms-1802-p",
     "https://www.cms.gov/regulations-and-guidance/guidance/transmittals/transmittals/r11035cp",
     "https://www.cms.gov/medicare/regulations-guidance/transmittals/2017-transmittals?items_per_page=25&order=field_dyna_transmittal_number&page=14&sort=asc",
     "https://www.cms.gov/regulations-and-guidance/guidance/transmittals/transmittals/r11929cp",
     "https://www.cms.gov/medicare/audits-compliance/part-c-part-d-compliance-audits/part-c-utilization-management-um-annual-data-submission",
     "https://www.cms.gov/medicare/regulations-guidance/transmittals/2026-transmittals/r13792cp"
    ]
   }
  ]
 },
 "enginesRun": {
  "sustainability": 30,
  "axe": 83,
  "resources": 83,
  "images": 40,
  "standards": 37,
  "lighthouse": 29,
  "link-check": 83,
  "plain-language": 53,
  "tech": 7,
  "security": 9,
  "alfa": 27,
  "deprecated-html": 16
 },
 "tally": {
  "ok": 83,
  "blocked": 1,
  "timeout": 0,
  "robots_skipped": 2,
  "url_filtered": 0,
  "non_html": 14,
  "error": 0
 },
 "finishedAt": "2026-06-17T11:38:16.325Z"
}