{"pageId":"9daaaf09916b7b86","url":"https://data.cms.gov/tools/medicare-inpatient-hospital-look-up-tool","week":"2026-W26","runId":"2026-06-23T08-37-01-933Z-04cdfa","scannedAt":"2026-06-23T08:55:44.889Z","status":200,"depth":1,"axe":{"engine":"axe-core","version":"4.12.1","violationCount":4,"violations":{"label-title-only":{"count":1,"impact":"serious","help":"Form elements should have a visible label","helpUrl":"https://dequeuniversity.com/rules/axe/4.12/label-title-only?application=axeAPI","tags":["best-practice"],"examples":[{"target":"#react-select-2-input","html":"<input class=\"InteractiveToolsSear...\" autocapitalize=\"none\" autocomplete=\"off\" autocorrect=\"off\" id=\"react-select-2-input\" spellcheck=\"false\" tabindex=\"0\" type=\"text\" aria-autocomplete=\"list\" aria-ex"}]},"label":{"count":1,"impact":"critical","help":"Form elements must have labels","helpUrl":"https://dequeuniversity.com/rules/axe/4.12/label?application=axeAPI","tags":["wcag2a","wcag412"],"examples":[{"target":"#react-select-2-input","html":"<input class=\"InteractiveToolsSear...\" autocapitalize=\"none\" autocomplete=\"off\" autocorrect=\"off\" id=\"react-select-2-input\" spellcheck=\"false\" tabindex=\"0\" type=\"text\" aria-autocomplete=\"list\" aria-ex"}]},"landmark-banner-is-top-level":{"count":1,"impact":"moderate","help":"Banner landmark should not be contained in another landmark","helpUrl":"https://dequeuniversity.com/rules/axe/4.12/landmark-banner-is-top-level?application=axeAPI","tags":["best-practice"],"examples":[{"target":".Header","html":"<header class=\"Header\" style=\"position: sticky;\">"}]},"landmark-unique":{"count":1,"impact":"moderate","help":"Landmarks should have a unique role or role/label/title (i.e. accessible name) combination","helpUrl":"https://dequeuniversity.com/rules/axe/4.12/landmark-unique?application=axeAPI","tags":["best-practice"],"examples":[{"target":".desktop","html":"<nav aria-label=\"breadcrumb\" class=\"DatasetHero__breadcrumb desktop\">"}]}},"incompleteCount":13},"resources":{"engine":"resources","count":0,"byType":{},"resources":[]},"images":{"engine":"images","count":7,"images":[{"src":"https://data.cms.gov/assets/cms-header-logo-with-text-KO867bA3.svg","alt":"Centers for Medicare & Medicaid Services Data","hasAlt":true,"isDecorative":false,"isMissingAlt":false,"ariaHidden":false,"rolePresentation":false,"renderedWidth":270,"renderedHeight":45,"naturalWidth":300,"naturalHeight":50,"loading":null,"decoding":null,"altVerdict":"GOOD","altReason":"present, no red flags","bytes":3623},{"src":"https://data.cms.gov/sites/default/files/2020-06/IPPS%20Hospital%20Look-Up.svg","alt":"Medicare Inpatient Hospitals","hasAlt":true,"isDecorative":false,"isMissingAlt":false,"ariaHidden":false,"rolePresentation":false,"renderedWidth":68,"renderedHeight":63,"naturalWidth":140,"naturalHeight":140,"loading":null,"decoding":null,"altVerdict":"GOOD","altReason":"present, no red flags","bytes":894},{"src":"https://data.cms.gov/assets/cms-header-logo-with-text-KO867bA3.svg","alt":"Centers for Medicare & Medicaid Services Data","hasAlt":true,"isDecorative":false,"isMissingAlt":false,"ariaHidden":false,"rolePresentation":false,"renderedWidth":300,"renderedHeight":50,"naturalWidth":300,"naturalHeight":50,"loading":null,"decoding":null,"altVerdict":"GOOD","altReason":"present, no red flags","bytes":3623},{"src":"https://data.cms.gov/assets/cms-header-logo-with-text-KO867bA3.svg","alt":"Centers for Medicare & Medicaid Services Data","hasAlt":true,"isDecorative":false,"isMissingAlt":false,"ariaHidden":false,"rolePresentation":false,"renderedWidth":300,"renderedHeight":50,"naturalWidth":300,"naturalHeight":50,"loading":null,"decoding":null,"altVerdict":"GOOD","altReason":"present, no red flags","bytes":3623},{"src":"https://data.cms.gov/assets/hhsLogo-dropYHmJ.png","alt":"U.S. Department of Health & Human Services","hasAlt":true,"isDecorative":false,"isMissingAlt":false,"ariaHidden":false,"rolePresentation":false,"renderedWidth":60,"renderedHeight":61,"naturalWidth":1974,"naturalHeight":1991,"loading":null,"decoding":null,"altVerdict":"GOOD","altReason":"present, no red flags","bytes":54560},{"src":"https://data.cms.gov/assets/dataCmsLogoWhite-_eNoRlxG.png","alt":"Centers for Medicare & Medicaid Services Data logo","hasAlt":true,"isDecorative":false,"isMissingAlt":false,"ariaHidden":false,"rolePresentation":false,"renderedWidth":182,"renderedHeight":27,"naturalWidth":504,"naturalHeight":76,"loading":null,"decoding":null,"altVerdict":"GOOD","altReason":"present, no red flags","bytes":8609},{"src":"https://data.cms.gov/assets/backToTop-DKOaMnxd.svg","alt":"back to top","hasAlt":true,"isDecorative":false,"isMissingAlt":false,"ariaHidden":false,"rolePresentation":false,"renderedWidth":60,"renderedHeight":60,"naturalWidth":150,"naturalHeight":150,"loading":null,"decoding":null,"altVerdict":"GOOD","altReason":"present, no red flags","bytes":2141}]}}