{"pageId":"0aac25282ba11fc5","url":"https://data.cms.gov/provider-data/dataset/tee5-ixt5?page=3","week":"2026-W25","runId":"2026-06-16T12-44-13-799Z-6ddaec","scannedAt":"2026-06-16T12:48:38.017Z","status":200,"depth":4,"sustainability":{"engine":"sustainability","requests":26,"bytes":3664158,"byType":{"document":667408,"script":1729504,"stylesheet":159216,"xhr":31039,"image":19894,"fetch":12297,"font":1044800},"co2g":0.543,"energyWh":1.0992,"model":"swd-v4 (co2.js)"},"axe":{"engine":"axe-core","version":"4.12.1","violationCount":0,"violations":{},"incompleteCount":277},"resources":{"engine":"resources","count":2,"byType":{"spreadsheet":1,"pdf":1},"resources":[{"url":"https://data.cms.gov/provider-data/sites/default/files/resources/346a4dd2d0f21e2aeaf90f7e4c5e31de_1775505947/HH_State_Apr2026.csv","type":"spreadsheet"},{"url":"https://data.cms.gov/provider-data/sites/default/files/data_dictionaries/home_health/HHS_Data_Dictionary.pdf","type":"pdf"}]}}