{"pageId":"9470c8be40cafca1","url":"https://data.cms.gov/resources/medicare-durable-medical-equipment-devices-supplies-by-referring-provider-and-service-data-dictionary-2021","week":"2026-W25","runId":"2026-06-15T10-02-23-874Z-cb9a98","scannedAt":"2026-06-15T10:32:31.448Z","status":200,"depth":1,"axe":{"engine":"axe-core","version":"4.12.1","violationCount":2,"violations":{"heading-order":{"count":1,"impact":"moderate","help":"Heading levels should only increase by one","helpUrl":"https://dequeuniversity.com/rules/axe/4.12/heading-order?application=axeAPI","tags":["best-practice"],"examples":[{"target":".ArticleSearchBox__label","html":"<h3 class=\"typeface-05-H5-Black-Regular-L ArticleSearchBox__label\">Search for keywords</h3>"}]},"landmark-banner-is-top-level":{"count":1,"impact":"moderate","help":"Banner landmark should not be contained in another landmark","helpUrl":"https://dequeuniversity.com/rules/axe/4.12/landmark-banner-is-top-level?application=axeAPI","tags":["best-practice"],"examples":[{"target":".Header","html":"<header class=\"Header\" style=\"position: sticky;\">"}]}},"incompleteCount":2},"plainLanguage":{"engine":"plain-language","scored":false,"wordCount":1566,"misspelledCount":224,"misspelled":["govA","https","DictionaryMedicare","DownloadPage","modifiedOctober","definitionsDefinitionsDefinitionsSearch","keywordsNo","matchesReferring","NPIVariable","nameRfrg","NPIDefinitionNational","NameVariable","Prvdr","NameDefinitionWhen","InitialVariable","MIDefinitionWhen","CredentialsVariable","CrdntlsDefinitionWhen","GenderVariable","GnderDefinitionWhen","CodeVariable","Ent","CdDefinitionType","DefinitionThe","CityVariable"],"sentenceCount":35,"fleschReadingEase":null,"fleschKincaidGrade":null,"avgSentenceLength":null,"longSentences":0,"passiveVoiceRatio":null,"unexplainedAcronyms":["HTTPSA","DMEPOS","NPPES","AA","AE","AP","AS","GU","MP","PR","VI","ZZ","FIPS","ZIP","US","NDC","WW","RR","MD"],"unexplainedAcronymCount":19},"deprecatedHtml":{"engine":"deprecated-html","findingCount":0,"findings":{}},"resources":{"engine":"resources","count":1,"byType":{"pdf":1},"resources":[{"url":"https://data.cms.gov/sites/default/files/2021-08/mup_dme_ry21_20210822_dd_prvhp.pdf","type":"pdf"}]},"sustainability":{"engine":"sustainability","requests":62,"bytes":1632375,"byType":{"document":484,"stylesheet":154367,"script":1083623,"image":101325,"font":245544,"xhr":46645,"fetch":387},"co2g":0.2419,"energyWh":0.4897,"model":"swd-v4 (co2.js)"}}