{
 "runId": "2026-06-24T08-24-50-734Z-6c81e3",
 "week": "2026-W26",
 "domain": "data.medicaid.gov",
 "startedAt": "2026-06-24T08:24:52.775Z",
 "scanned": [
  "2ea7849c225fa96f",
  "e0cb39d80935e752",
  "fa937b072367b281",
  "cea5f59b0c2cb565",
  "e722971a67394e95",
  "c3f5bd88183fb04d",
  "f180bd0e7acf427b",
  "0cd27f404beb174d",
  "89867fa214f82b89",
  "eb504bc02537cb63",
  "8ca35abefcedfc5b",
  "70bac9a7f67fc369",
  "a7a8216a9d160aa0",
  "bdb51ee20c8c6f10",
  "c0f2ad763dc8f897",
  "8a55da4d4ca8bc08",
  "239badf7dec02a4e",
  "673abb5ab72886f3",
  "06be7f20b9719b70",
  "4bea19b82f119c0b",
  "58be028eb870ef5a",
  "fe43666b64fc5c5c",
  "fa766c0fea8b3141",
  "399e64632a7a4e01",
  "cfbd368722d46189",
  "29e965bcbd907917",
  "19ae2d51dbf3d15b",
  "ee5f9fab66e95c06",
  "b5a244015f9ad68d",
  "b8f2161edf37db46",
  "2b5d297082c17708",
  "6b04b41daaf98de7",
  "70380cdfc39b0d3c",
  "6326372110ab69b2",
  "43fafa964fba64a9",
  "092acec6561cc1db",
  "fb748c83b3d3d728",
  "ab00d1baba84a5d0",
  "46089a96c7e3a3e9",
  "dc40ee6b80739f3f",
  "10d409e3e10a4bfa",
  "2bdc4a8650784a5a",
  "6e6e1e3313ed8a18",
  "469236b19e44975f",
  "23065584fb6430ec",
  "06faf91c9ccb9f3f",
  "512d53753bf33456",
  "d86442d5607d2be4",
  "923ca65dd9c6109a",
  "c08ad034e7c9b839",
  "ea591280368d601a",
  "1894a63569f6f5b1",
  "594f16add6c9be9d",
  "ff086e2aa773ce1e",
  "bce25c0cd5d7974a",
  "028608438a5035d5",
  "436fcb96a502e7f0",
  "8d55e90a934c36f5",
  "2dd507d611de2bbb",
  "cdf556f3faf88906",
  "6fc25c914270ba0c",
  "f7b72b0b00da0344",
  "e9167d35b7388a17",
  "71b30ff7fdcf7db7",
  "9ece3746bbd28d94",
  "8b4f2d6078ab87c0",
  "f56b27bbf56e14d1",
  "8b1a788c8c8c8fb4",
  "5ac561e10fe25f1c",
  "4ae3ec3eddb2c0eb",
  "6735ab4bd8f682fa",
  "4dabeeebc8ce1804",
  "fc07813932f85432",
  "ca5d23d9517f4232",
  "2a4c575abdf51a62",
  "e78074e63e554791",
  "b18b1a4fe4cb8500",
  "9735d53ac4e859ca",
  "a3309f4726de7c04",
  "93625710a2721a69",
  "691b4afef5875b53",
  "921b32c8b33270fd",
  "0e47f07c6556d2f8",
  "cfac622dc145c56c",
  "6f194d156ec16405",
  "d2792256d4d58092",
  "635b71a49b7b103b",
  "4cc7e8a853c0c1b7",
  "8d6aacf6732d7ec8",
  "a155b72f9ee6d76f",
  "93af847e54a96058",
  "8d21617160561d1a",
  "dba6e14b8b06d2e0",
  "8c126867be2c7722",
  "a660e4ea0a815ea0",
  "6b669cbfcadc5c8d",
  "36bb33ce005549dd",
  "4124bdf5e0160920",
  "e2ab0ecfefc6a67f",
  "d88d9fe4482bf2d0",
  "b2e667cddfcca64a",
  "38b9abeb85401b39",
  "26585c1089566f3c",
  "7cdbf26011ea7662",
  "bfdf2b8f80f98d91",
  "7fa355878574f676",
  "34d7972bcbcb38f6",
  "29a97e01b012be37",
  "5bfa2e79729805a8",
  "697a7a1748ac73e6",
  "9f8361342193e0c0",
  "cf7d89095ff50946",
  "e922adce4140c7f0",
  "a696f137fd31f81d",
  "8b2be7c3cc74dfef",
  "76e9637d93e0728a",
  "054cbee8a7fdc3c8",
  "828b5bfdae6a519c",
  "f226d7db22c414fa",
  "fbdad92d692301e1",
  "f4fd20d943327926",
  "26d9514205e2eae9",
  "46fb6ac96ec043b8",
  "44a5fc9cf74a7b47",
  "68ada5ff8c58f9ba",
  "50a3f05fd735508f",
  "c39bfac1f691234b",
  "ce1402aeadcdc673",
  "a1d17fcc1d847a81",
  "eb5a5811559dd82a",
  "79a3e3763425ca86",
  "e6a85ea04d97c8c9",
  "5319ee0287135ffc",
  "b08578138c12c735",
  "7a82fd7d53cdb8b7",
  "3728fcb220420620",
  "4becbb929fa47f7d",
  "242571c00152cb71",
  "f9101d31e8e73d81",
  "4b4ce45d554cae25",
  "c5c9732cf11444d1",
  "a87ef5985d0861af",
  "1c13efc7de4f6f2e",
  "e147ca0f6961b1ff",
  "feaee0ceae64d2db",
  "e15b45addc6f7ae0",
  "a1c94f3a55ad7387",
  "9e262e3855e7b33e",
  "ea61571a7da60525",
  "c6c385ecaff850ad"
 ],
 "errors": [],
 "sampling": {
  "axe": 100,
  "alfa": 50,
  "plain-language": 50,
  "link-check": 100,
  "lighthouse": 10,
  "deprecated-html": 10,
  "resources": 100,
  "images": 100,
  "standards": 50,
  "security": 10,
  "public-interest": 10,
  "sustainability": 10,
  "tech": 10,
  "third-party": 25
 },
 "linkCheck": {
  "total": 957,
  "checked": 500,
  "brokenCount": 3,
  "broken": [
   {
    "url": "https://data.medicaid.gov/whats-new",
    "status": 404,
    "reason": "HTTP 404",
    "foundOn": [
     "https://data.medicaid.gov/dataset/651fa253-4dd4-4867-8725-2b5ae1dd5ce9?page=2",
     "https://data.medicaid.gov/dataset/1db0f12c-e4d6-5a70-8c1b-5af9635999be?page=4",
     "https://data.medicaid.gov/dataset/79692ea5-21e1-56bf-8149-97d437120c4b?page=5",
     "https://data.medicaid.gov/dataset/2aa0ed3d-6ef8-47a8-90b0-06b6d2fa3953?page=128",
     "https://data.medicaid.gov/dataset/d30cfc7c-4b32-4df1-b2bf-e0a850befd77?page=32",
     "https://data.medicaid.gov/dataset/49d67dfc-9432-4f63-bb99-a3eacf8bf93e?page=4",
     "https://data.medicaid.gov/dataset/2b18f2f7-d0f3-5efe-afc4-4881fcbdf200?page=3",
     "https://data.medicaid.gov/dataset/e93bf3fa-e92e-5bfe-b8e8-552ca8f9d499?page=2",
     "https://data.medicaid.gov/dataset/22c72566-87de-5759-90ee-350df11bc89b?page=3",
     "https://data.medicaid.gov/dataset/99a60727-dc56-5dc2-a72c-5b2e71078ad6?page=39",
     "https://data.medicaid.gov/dataset/eba2c172-07ba-4a6a-877e-5373ca442243?page=4",
     "https://data.medicaid.gov/dataset/67483256-e996-4342-9867-fc0b6a67230f?page=3",
     "https://data.medicaid.gov/dataset/935a5667-0da1-56a5-8a7a-e5e4135abd06?page=3",
     "https://data.medicaid.gov/dataset/d55e5ef5-9a2e-4d6c-884e-65a40a70756b",
     "https://data.medicaid.gov/dataset/fc3c7c14-4b08-59c2-97db-0726e478dfdf?page=2",
     "https://data.medicaid.gov/dataset/5abea2e0-3f8e-4b49-a50d-d63d5fd9103c?page=4",
     "https://data.medicaid.gov/dataset/e85033c7-367e-467e-9e81-8e85048102b8?page=227",
     "https://data.medicaid.gov/dataset/e2ce0d2f-07c5-5213-947a-31e19bc649f6?page=5",
     "https://data.medicaid.gov/dataset/a211a52d-278d-4509-87a9-cdc6af256f31?page=4",
     "https://data.medicaid.gov/dataset/509b91a3-0fb5-449a-bbf2-40e987e45ed3?page=3",
     "https://data.medicaid.gov/datasets?keyword%5B0%5D=chip&page=2",
     "https://data.medicaid.gov/dataset/72135da5-f8b4-475b-b602-91621f4205d9?page=2",
     "https://data.medicaid.gov/datasets?keyword%5B%5D=acute+care",
     "https://data.medicaid.gov/dataset/e2893fe7-8869-45c9-bb4c-9eb20dc2bd33?page=3",
     "https://data.medicaid.gov/dataset/a8647354-7dcb-5949-9582-b40e7a985bef?page=231",
     "https://data.medicaid.gov/dataset/6de859d5-5ea7-42df-b5aa-1fc22c4b35a1?page=4",
     "https://data.medicaid.gov/dataset/cfbf62b6-ab10-46d1-9284-b08475964470?page=7",
     "https://data.medicaid.gov/dataset/ebcfc16f-8291-4c61-82a4-055846d72f3a/data?page=3",
     "https://data.medicaid.gov/datasets?theme%5B0%5D=National+Average+Drug+Acquisition+Cost",
     "https://data.medicaid.gov/dataset/f3713443-bbec-59ad-a660-fb6c599f23d3?page=3",
     "https://data.medicaid.gov/dataset/a7145ad2-4779-506c-8823-7651a651e031?page=4",
     "https://data.medicaid.gov/dataset/cb8d7614-bf80-5ffd-a166-4f3903f1ddd4?page=5",
     "https://data.medicaid.gov/datasets?keyword%5B0%5D=DQ+Atlas&page=3",
     "https://data.medicaid.gov/dataset/e55bd3f1-1645-5751-8b2e-803f5c1b76ef",
     "https://data.medicaid.gov/dataset/85272998-7ec9-4bd9-87ef-8c75156436ac?page=2",
     "https://data.medicaid.gov/dataset/7a7af4ad-3403-5ad7-8983-b2db6c203a82?page=3",
     "https://data.medicaid.gov/dataset/99a60727-dc56-5dc2-a72c-5b2e71078ad6?page=4",
     "https://data.medicaid.gov/dataset/bd782837-31ac-41ae-9569-52182bc038e9?page=3",
     "https://data.medicaid.gov/dataset/85272998-7ec9-4bd9-87ef-8c75156436ac?page=5",
     "https://data.medicaid.gov/dataset/00505e90-f8ac-5921-b12f-5e23ba7ffcf3?page=4",
     "https://data.medicaid.gov/dataset/3da9f4e6-7976-43a8-8d1b-72f2c557a5ca?page=5",
     "https://data.medicaid.gov/dataset/55978f20-d0db-49a0-a304-1c4471367a95?page=2",
     "https://data.medicaid.gov/datasets?keyword%5B%5D=nadac",
     "https://data.medicaid.gov/dataset/9c9ad0d1-c59b-4a25-9314-8e7e44e7f281?page=2",
     "https://data.medicaid.gov/dataset/c216cbc6-cea3-5111-94c2-c5059c2f94cf?page=5",
     "https://data.medicaid.gov/dataset/d30cfc7c-4b32-4df1-b2bf-e0a850befd77",
     "https://data.medicaid.gov/dataset/58d9a2f4-82e2-5603-af3f-90338b11fbe7?page=3",
     "https://data.medicaid.gov/dataset/78950031-dea0-53d7-9247-d5affba75d96?page=4",
     "https://data.medicaid.gov/dataset/c21bff91-35f5-5333-9bf5-ffd895d96c6a?page=42",
     "https://data.medicaid.gov/dataset/819b3417-0f93-488d-974a-4f80c87eb48f?page=3"
    ]
   },
   {
    "url": "https://data.medicaid.gov/page=2",
    "status": 404,
    "reason": "HTTP 404",
    "foundOn": [
     "https://data.medicaid.gov/dataset/5abea2e0-3f8e-4b49-a50d-d63d5fd9103c?page=4",
     "https://data.medicaid.gov/dataset/e2893fe7-8869-45c9-bb4c-9eb20dc2bd33?page=3",
     "https://data.medicaid.gov/dataset/93c14523-3acb-4253-a9e0-98b0bd201541?page=2",
     "https://data.medicaid.gov/dataset/5abea2e0-3f8e-4b49-a50d-d63d5fd9103c?page=5",
     "https://data.medicaid.gov/dataset/91f52654-d9cd-46f9-8393-c266e1fd2cba",
     "https://data.medicaid.gov/dataset/0a84adcc-7bc8-4293-a6f9-11937596ad37?page=5",
     "https://data.medicaid.gov/dataset/19244215-9767-43ae-b436-0d5b1250c0a1?page=7",
     "https://data.medicaid.gov/dataset/d906204c-3476-4a75-bd35-342b8dc56687?page=2",
     "https://data.medicaid.gov/dataset/df124eb9-35d9-48d1-b879-ff52f9fef128?page=2"
    ]
   },
   {
    "url": "https://data.medicaid.gov/api/1/metastore/schemas/data-dictionary/items/66f843c8-1180-4244-8adc-554d02584fa4/csv",
    "status": 404,
    "reason": "HTTP 404",
    "foundOn": [
     "https://data.medicaid.gov/dataset/e2893fe7-8869-45c9-bb4c-9eb20dc2bd33?page=3",
     "https://data.medicaid.gov/dataset/93c14523-3acb-4253-a9e0-98b0bd201541?page=2",
     "https://data.medicaid.gov/dataset/91f52654-d9cd-46f9-8393-c266e1fd2cba",
     "https://data.medicaid.gov/dataset/19244215-9767-43ae-b436-0d5b1250c0a1?page=7",
     "https://data.medicaid.gov/dataset/d906204c-3476-4a75-bd35-342b8dc56687?page=2",
     "https://data.medicaid.gov/dataset/df124eb9-35d9-48d1-b879-ff52f9fef128?page=2"
    ]
   }
  ]
 },
 "enginesRun": {
  "axe": 121,
  "plain-language": 61,
  "resources": 121,
  "images": 121,
  "link-check": 121,
  "alfa": 61,
  "standards": 55,
  "security": 13,
  "third-party": 24,
  "deprecated-html": 10,
  "sustainability": 13,
  "public-interest": 12,
  "lighthouse": 11,
  "tech": 11
 },
 "tally": {
  "ok": 121,
  "blocked": 0,
  "timeout": 0,
  "robots_skipped": 0,
  "url_filtered": 0,
  "non_html": 29,
  "error": 0
 },
 "finishedAt": "2026-06-24T08:42:43.835Z"
}