{
 "runId": "2026-06-17T10-08-24-150Z-cb1858",
 "week": "2026-W25",
 "domain": "www.medicaid.gov",
 "startedAt": "2026-06-17T10:08:25.428Z",
 "scanned": [
  "85eb6750a3042891",
  "5b9dbf4090d13258",
  "7ebf7980536ddf23",
  "125500f07b72b2e8",
  "0149797d4f4e6713",
  "cc7eb3401cff8bcf",
  "dac32c57c2a0207c",
  "93d1e5b4b0216839",
  "da67e3b0d05f65b1",
  "4ebec0c5b54d9846",
  "43fd93be51da003b",
  "725245acbcc9d49a",
  "a8cc92452fb2cc5b",
  "bb22689b6f6c7050",
  "ca648c1e3f8a045f",
  "0edcb884635c1702",
  "98b5ec07fb4676e4",
  "e2eb0ab3cb7e65ea",
  "59fbc187ccaa756a",
  "1c863af54337da38",
  "9fbf25f9c1e696cd",
  "c6e9fd6234689f4d",
  "eead4a60c06bddc6",
  "ef5d1a72c7c4c69e",
  "176daed661aa3578",
  "1315246934de303e",
  "1b33767d1dea749f",
  "6fdab900fb763df4",
  "d402065f48270dbb",
  "85ac86ffd71d8e67",
  "4a930edf4be39299",
  "c47444e7b76fc29a",
  "2d83dca002aba6f2",
  "760d3f33e104266b",
  "777b896f23c55c8d",
  "d96b7d7006102aed",
  "8eb5d7d8f8c8af00",
  "6c7339bcc1f41f0e",
  "b0a6608dfe81a72e",
  "82651b8aa77ff2da",
  "7fbda8395b102f08",
  "57b3393f2734e46a",
  "dead9fb7b5f4394b",
  "a7f5b37e666967a5",
  "d6deb9ac95c8f0d3",
  "82d1b2bb17e18e16",
  "2ab1c613eab3d756",
  "cd192eda2fcac06e",
  "b9b05f69a1788de6",
  "eab459e61ea597ba",
  "ca1eb30ea8f85d78",
  "44220e1528626bd0",
  "b684e3091ea6f7b4",
  "9d01742100081224",
  "5a323dc8c937f5b2",
  "d55a098e5984d290",
  "b29c7079bb511232",
  "78050c5eacbb437b",
  "4cdc8bb0463ef9dc",
  "0be7bc6dfb0631ac",
  "abeed5ca52db1849",
  "9a4487612f32a7e5",
  "b2de270c7cce57f8",
  "9a971b4d9c8787aa",
  "11477c9435dcdae9",
  "2e2708e36dc5637a",
  "107ac82a46ce4502",
  "825d47aa91a5df68",
  "b0dce02dd0d061a7",
  "fc5fee457f3befeb",
  "2cddc4910840d4c0",
  "4e6824bf84cde751",
  "68fed72e30bd2974",
  "b82b4cd9a5ce1b0a",
  "5d2903cd44245b8e",
  "860facbd584a849f",
  "65f112ea0d3101f0",
  "a6a0e3b98d5daf1f",
  "a93c224a9b23293c",
  "3153af15ed4e458c",
  "6de3038bdb052001",
  "d3da628f9e581eb6",
  "216cb2de6f0f605a",
  "4894ad342849503d",
  "e87723d36cde8ca7",
  "388e14d5822cda74",
  "c737093bcc7868af",
  "ec58706864855f67",
  "bc1bf39e3ae861d8",
  "803790e1a4d506fe",
  "c6c6655a08624ed7",
  "fee8bf752d2d7f6f",
  "0fb578908578d0b8",
  "d6ae5eaa2c6df0f5",
  "1a051f3edfabe125",
  "7f6ce2c86ad7af01",
  "afb8284888a17921",
  "d1f20f2065d4a6bf",
  "0aebe30a9a384e39",
  "b1daf68338bdeea3"
 ],
 "errors": [],
 "sampling": {
  "axe": 100,
  "alfa": 30,
  "plain-language": 50,
  "link-check": 100,
  "lighthouse": 25,
  "deprecated-html": 25,
  "resources": 100,
  "images": 50,
  "standards": 50,
  "security": 10,
  "sustainability": 25,
  "tech": 10
 },
 "linkCheck": {
  "total": 1288,
  "checked": 500,
  "brokenCount": 0,
  "broken": []
 },
 "enginesRun": {
  "sustainability": 32,
  "axe": 98,
  "resources": 98,
  "link-check": 98,
  "alfa": 34,
  "deprecated-html": 25,
  "standards": 49,
  "images": 52,
  "plain-language": 45,
  "lighthouse": 26,
  "tech": 9,
  "security": 7
 },
 "tally": {
  "ok": 98,
  "blocked": 0,
  "timeout": 0,
  "robots_skipped": 0,
  "url_filtered": 0,
  "non_html": 2,
  "error": 0
 },
 "finishedAt": "2026-06-17T10:20:19.564Z"
}