{"pageId":"32884420ffc5541d","url":"http://www.cms.gov/apps/acronyms","week":"2026-W26","runId":"2026-06-27T12-03-45-837Z-5686a0","scannedAt":"2026-06-27T12:09:48.486Z","status":200,"depth":4,"sustainability":{"engine":"sustainability","requests":55,"bytes":2054467,"byType":{"document":30440,"image":4996,"script":1402773,"stylesheet":76994,"font":526184,"fetch":410,"xhr":12670},"co2g":0.3045,"energyWh":0.6163,"model":"swd-v4 (co2.js)"},"axe":{"engine":"axe-core","version":"4.12.1","violationCount":0,"violations":{},"incompleteCount":5},"plainLanguage":{"engine":"plain-language","scored":true,"wordCount":213,"misspelledCount":8,"misspelled":["cms","hhs","Shadoan","http","www","html","ActionPhase"],"sentenceCount":9,"fleschReadingEase":56.5,"fleschKincaidGrade":11.3,"avgSentenceLength":23.7,"longSentences":5,"passiveVoiceRatio":0,"unexplainedAcronyms":["CMS","AS","PT","OMB"],"unexplainedAcronymCount":4},"resources":{"engine":"resources","count":1,"byType":{"pdf":1},"resources":[{"url":"http://www.cms.gov/files/document/agent/broker-help-desks.pdf","type":"pdf"}]},"images":{"engine":"images","count":3,"images":[{"src":"https://www.cms.gov/themes/custom/cms_evo/logo.svg","alt":"CMS.gov","hasAlt":true,"isDecorative":false,"isMissingAlt":false,"ariaHidden":false,"rolePresentation":false,"renderedWidth":170,"renderedHeight":41,"naturalWidth":300,"naturalHeight":72,"loading":null,"decoding":null,"altVerdict":"GOOD","altReason":"present, no red flags","bytes":2086},{"src":"https://www.cms.gov/themes/custom/cms_evo/logo.svg","alt":"CMS.gov","hasAlt":true,"isDecorative":false,"isMissingAlt":false,"ariaHidden":false,"rolePresentation":false,"renderedWidth":167,"renderedHeight":40,"naturalWidth":300,"naturalHeight":72,"loading":null,"decoding":null,"altVerdict":"GOOD","altReason":"present, no red flags","bytes":2086},{"src":"https://www.cms.gov/themes/custom/cms_evo/images/hhslogo.png","alt":"HHS Logo","hasAlt":true,"isDecorative":false,"isMissingAlt":false,"ariaHidden":false,"rolePresentation":false,"renderedWidth":52,"renderedHeight":52,"naturalWidth":65,"naturalHeight":65,"loading":null,"decoding":null,"altVerdict":"GOOD","altReason":"present, no red flags","bytes":2762}]}}